php_ast/__init__.py
php_ast/libphp7.so
php_ast/php_ast.py
php_ast/php_ast_test.py
php_ast-1.5.dist-info/LICENSE
php_ast-1.5.dist-info/METADATA
php_ast-1.5.dist-info/WHEEL
php_ast-1.5.dist-info/top_level.txt
php_ast-1.5.dist-info/RECORD
