Metadata-Version: 2.1
Name: php-ast
Version: 1.5
Summary: A Python package for php_ast
Home-page: https://github.com/php-ast/php_ast
Author: php_ast
Author-email: 20200120614@nxmu.edu.cn
Classifier: Programming Language :: Python :: 3
Classifier: License :: OSI Approved :: MIT License
License-File: LICENSE
